{
	"name": "MenuBoneLeft",
	"plugin-id": "Sprite",
	"sid": 5246535965326995,
	"isGlobal": false,
	"instanceVariables": [
		{
			"name": "Timer",
			"type": "number",
			"desc": "",
			"sid": 7519107776133302
		},
		{
			"name": "Destroy",
			"type": "boolean",
			"desc": "",
			"sid": 6433670307252687
		}
	],
	"behaviorTypes": [],
	"effectTypes": [],
	"animations": {
		"items": [
			{
				"frames": [
					{
						"width": 14,
						"height": 44,
						"originX": 0,
						"originY": 0,
						"originalSource": "D:\\Documents\\Undertale Rip\\Sprites\\spr_s_boneloop_out_0.png",
						"exportFormat": "png",
						"exportQuality": 0.8,
						"imageSpriteId": 79,
						"collisionPoly": {
							"points": [
								0.142857,
								0.0454545,
								0.857143,
								0.0454545,
								0.857143,
								0.954545,
								0.142857,
								0.954545
							]
						},
						"useCollisionPoly": true,
						"duration": 1
					}
				],
				"sid": 1189648859175843,
				"name": "Default",
				"isLooping": false,
				"isPingPong": false,
				"repeatCount": 1,
				"repeatTo": 0,
				"speed": 5
			}
		],
		"subfolders": []
	}
}